AlpacaAccountData/AccountData.py
AlpacaAccountData/__init__.py
AlpacaAccountData-0.0.7.dist-info/METADATA
AlpacaAccountData-0.0.7.dist-info/WHEEL
AlpacaAccountData-0.0.7.dist-info/top_level.txt
AlpacaAccountData-0.0.7.dist-info/RECORD
