Metadata-Version: 2.1
Name: AlpacaAccountData
Version: 0.0.7
Summary: Manage Alpaca accounts via office utils.
Author-email: Hunter Dale <guyyatsu@gmail.com>
Project-URL: Homepage, https://github.com/guyyatsu/Broker-Bot
Project-URL: Bug Tracker, https://github.com/guyyatsu/Broker-Bot/issues
Classifier: Programming Language :: Python :: 3
Classifier: License :: OSI Approved :: MIT License
Classifier: Operating System :: OS Independent
Requires-Python: >=3.7
Requires-Dist: CredentialManagement
Requires-Dist: alpaca-py
